dymoapi/__init__.py
dymoapi/config.py
dymoapi/dymoapi.py
dymoapi/exceptions.py
dymoapi/response_models.py
dymoapi/branches/__init__.py
dymoapi/branches/private.py
dymoapi/branches/public.py
dymoapi/resilience/__init__.py
dymoapi/resilience/fallback.py
dymoapi/services/__init__.py
dymoapi/services/autoupload.py
dymoapi/utils/__init__.py
dymoapi/utils/basics.py
dymoapi/utils/decorators.py
dymoapi-0.0.65.dist-info/licenses/LICENSE
tests/__init__.py
tests/test_dymoapi.py
tests/test_resilience.py
dymoapi-0.0.65.dist-info/METADATA
dymoapi-0.0.65.dist-info/WHEEL
dymoapi-0.0.65.dist-info/top_level.txt
dymoapi-0.0.65.dist-info/RECORD
