Metadata-Version: 2.4
Name: dymoapi
Version: 0.0.65
Summary: Dymo Python API library.
Home-page: https://github.com/TPEOficial/dymo-api-python
Author: TPEOficial LLC
Author-email: support@tpeoficial.com
License: Apache-2.0
Classifier: Programming Language :: Python :: 3
Classifier: License :: OSI Approved :: Apache Software License
Classifier: Operating System :: OS Independent
Requires-Python: >=3.6
License-File: LICENSE
Requires-Dist: requests>=2.25.1
Dynamic: author
Dynamic: author-email
Dynamic: classifier
Dynamic: description
Dynamic: description-content-type
Dynamic: home-page
Dynamic: license
Dynamic: license-file
Dynamic: requires-dist
Dynamic: requires-python
Dynamic: summary
